shelldog/__init__.py
shelldog/cli.py
shelldog/logger.py
shelldog/shell_hook.py
shelldog-0.1.0.dist-info/licenses/LICENSE
shelldog-0.1.0.dist-info/METADATA
shelldog-0.1.0.dist-info/WHEEL
shelldog-0.1.0.dist-info/entry_points.txt
shelldog-0.1.0.dist-info/top_level.txt
shelldog-0.1.0.dist-info/RECORD
