Metadata-Version: 2.4
Name: shelldog
Version: 0.1.0
Summary: 🐕 Your loyal companion for tracking shell commands - silent, smart, and adorable!
Home-page: https://github.com/Ansumanbhujabal/shelldog
Author: Ansuman Bhujabala
Author-email: Ansuman Bhujabala <ansumanbhujabala@gmail.com>
License: MIT
Project-URL: Homepage, https://github.com/Ansumanbhujabal/shelldog
Project-URL: Bug Tracker, https://github.com/Ansumanbhujabal/shelldog/issues
Project-URL: Documentation, https://github.com/Ansumanbhujabal/shelldog/blob/main/README.md
Project-URL: Source Code, https://github.com/Ansumanbhujabal/shelldog
Keywords: shell,terminal,command,history,tracking,logger,development,cli,bash,zsh
Classifier: Development Status :: 4 - Beta
Classifier: Intended Audience :: Developers
Classifier: Topic :: Software Development :: Libraries :: Python Modules
Classifier: Topic :: System :: Shells
Classifier: Topic :: Utilities
Classifier: License :: OSI Approved :: MIT License
Classifier: Programming Language :: Python :: 3
Classifier: Programming Language :: Python :: 3.7
Classifier: Programming Language :: Python :: 3.8
Classifier: Programming Language :: Python :: 3.9
Classifier: Programming Language :: Python :: 3.10
Classifier: Programming Language :: Python :: 3.11
Classifier: Programming Language :: Python :: 3.12
Classifier: Operating System :: POSIX :: Linux
Classifier: Operating System :: MacOS
Classifier: Environment :: Console
Requires-Python: >=3.7
License-File: LICENSE
Requires-Dist: click>=8.0.0
Dynamic: author
Dynamic: home-page
Dynamic: license-file
Dynamic: requires-python
